{
  "seizoen": "2013-2014",
  "geslacht": "dames",
  "kampioen": "Den Bosch",
  "stand": [
    {
      "positie": 1,
      "club": "SCHC",
      "gespeeld": 22,
      "gewonnen": 16,
      "gelijk": 4,
      "verloren": 2,
      "doelpunten_voor": 71,
      "doelpunten_tegen": 21,
      "doelsaldo": 50,
      "punten": 52,
      "zone": "playoff"
    },
    {
      "positie": 2,
      "club": "Den Bosch",
      "gespeeld": 22,
      "gewonnen": 16,
      "gelijk": 3,
      "verloren": 3,
      "doelpunten_voor": 84,
      "doelpunten_tegen": 25,
      "doelsaldo": 59,
      "punten": 51,
      "zone": "playoff"
    },
    {
      "positie": 3,
      "club": "Amsterdam",
      "gespeeld": 22,
      "gewonnen": 14,
      "gelijk": 5,
      "verloren": 3,
      "doelpunten_voor": 68,
      "doelpunten_tegen": 26,
      "doelsaldo": 42,
      "punten": 47,
      "zone": "playoff"
    },
    {
      "positie": 4,
      "club": "Laren",
      "gespeeld": 22,
      "gewonnen": 13,
      "gelijk": 4,
      "verloren": 5,
      "doelpunten_voor": 57,
      "doelpunten_tegen": 29,
      "doelsaldo": 28,
      "punten": 43,
      "zone": "playoff"
    },
    {
      "positie": 5,
      "club": "Hurley",
      "gespeeld": 22,
      "gewonnen": 10,
      "gelijk": 4,
      "verloren": 8,
      "doelpunten_voor": 47,
      "doelpunten_tegen": 38,
      "doelsaldo": 9,
      "punten": 34,
      "zone": ""
    },
    {
      "positie": 6,
      "club": "MOP",
      "gespeeld": 22,
      "gewonnen": 10,
      "gelijk": 1,
      "verloren": 11,
      "doelpunten_voor": 38,
      "doelpunten_tegen": 50,
      "doelsaldo": -12,
      "punten": 31,
      "zone": ""
    },
    {
      "positie": 7,
      "club": "Kampong",
      "gespeeld": 22,
      "gewonnen": 9,
      "gelijk": 4,
      "verloren": 9,
      "doelpunten_voor": 40,
      "doelpunten_tegen": 36,
      "doelsaldo": 4,
      "punten": 31,
      "zone": ""
    },
    {
      "positie": 8,
      "club": "Oranje Zwart",
      "gespeeld": 22,
      "gewonnen": 8,
      "gelijk": 6,
      "verloren": 8,
      "doelpunten_voor": 58,
      "doelpunten_tegen": 44,
      "doelsaldo": 14,
      "punten": 30,
      "zone": ""
    },
    {
      "positie": 9,
      "club": "hdm",
      "gespeeld": 22,
      "gewonnen": 8,
      "gelijk": 4,
      "verloren": 10,
      "doelpunten_voor": 40,
      "doelpunten_tegen": 64,
      "doelsaldo": -24,
      "punten": 28,
      "zone": ""
    },
    {
      "positie": 10,
      "club": "Pinoké",
      "gespeeld": 22,
      "gewonnen": 3,
      "gelijk": 4,
      "verloren": 15,
      "doelpunten_voor": 19,
      "doelpunten_tegen": 55,
      "doelsaldo": -36,
      "punten": 13,
      "zone": "playout"
    },
    {
      "positie": 11,
      "club": "Nijmegen",
      "gespeeld": 22,
      "gewonnen": 2,
      "gelijk": 5,
      "verloren": 15,
      "doelpunten_voor": 22,
      "doelpunten_tegen": 73,
      "doelsaldo": -51,
      "punten": 11,
      "zone": "degradatie"
    },
    {
      "positie": 12,
      "club": "HIC",
      "gespeeld": 22,
      "gewonnen": 0,
      "gelijk": 2,
      "verloren": 20,
      "doelpunten_voor": 14,
      "doelpunten_tegen": 97,
      "doelsaldo": -83,
      "punten": 2,
      "zone": "degradatie"
    }
  ],
  "playoffs": {
    "halve_finales": [],
    "finale": null,
    "kampioen": "",
    "playout": []
  },
  "wiki_pagina": "https://nl.wikipedia.org/wiki/Hoofdklasse_hockey_dames_2013/14",
  "bijgewerkt": "2026-03-31"
}