{
  "mikki_roberts": [
    {
      "datum": "2026-03-29T22:00:00.000Z",
      "titel": "Roberts houdt Tilburg in leven_ ‘De druk stond er vol op’",
      "bullet": "Hield Tilburg in leven met een overwinning op HGC.",
      "link": "https://drive.google.com/file/d/1l_F_RDSAuOXvXwmihc1HNduCV6WMo9Nn"
    },
    {
      "datum": "2026-03-29T22:00:00.000Z",
      "titel": "Roberts houdt Tilburg in leven_ ‘De druk stond er vol op’",
      "bullet": "Scoorde één doelpunt en gaf twee assists.",
      "link": "https://drive.google.com/file/d/1l_F_RDSAuOXvXwmihc1HNduCV6WMo9Nn"
    },
    {
      "datum": "2026-03-29T22:00:00.000Z",
      "titel": "Roberts houdt Tilburg in leven_ ‘De druk stond er vol op’",
      "bullet": "Terug van een langdurige heupblessure.",
      "link": "https://drive.google.com/file/d/1l_F_RDSAuOXvXwmihc1HNduCV6WMo9Nn"
    },
    {
      "datum": "2026-03-30T22:00:00.000Z",
      "titel": "Roberts houdt Tilburg in leven_ ‘De druk stond er vol op’",
      "bullet": "Scoorde één doelpunt en gaf twee assists in de wedstrijd.",
      "link": "https://drive.google.com/file/d/1ZxDtMdMIqkGteFs5ObV0lLPbnhPdvaZR"
    },
    {
      "datum": "2026-03-30T22:00:00.000Z",
      "titel": "Roberts houdt Tilburg in leven_ ‘De druk stond er vol op’",
      "bullet": "Keerde terug van een langdurige heupblessure en speelde een sleutelrol.",
      "link": "https://drive.google.com/file/d/1ZxDtMdMIqkGteFs5ObV0lLPbnhPdvaZR"
    },
    {
      "datum": "2026-03-30T22:00:00.000Z",
      "titel": "Roberts houdt Tilburg in leven_ ‘De druk stond er vol op’",
      "bullet": "Maakt haar rentree in het Nederlands elftal tegen België.",
      "link": "https://drive.google.com/file/d/1ZxDtMdMIqkGteFs5ObV0lLPbnhPdvaZR"
    }
  ],
  "daphne_nikkels": [
    {
      "datum": "2026-03-29T22:00:00.000Z",
      "titel": "Roberts houdt Tilburg in leven_ ‘De druk stond er vol op’",
      "bullet": "Viel voor rust geblesseerd uit met een knieblessure.",
      "link": "https://drive.google.com/file/d/1l_F_RDSAuOXvXwmihc1HNduCV6WMo9Nn"
    },
    {
      "datum": "2026-03-30T22:00:00.000Z",
      "titel": "Roberts houdt Tilburg in leven_ ‘De druk stond er vol op’",
      "bullet": "Ervaren aanvaller die voor rust geblesseerd uitviel met een knieblessure.",
      "link": "https://drive.google.com/file/d/1ZxDtMdMIqkGteFs5ObV0lLPbnhPdvaZR"
    },
    {
      "datum": "2026-03-30T22:00:00.000Z",
      "titel": "Roberts houdt Tilburg in leven_ ‘De druk stond er vol op’",
      "bullet": "Haar blessure dwong Tilburg tot het schuiven met posities.",
      "link": "https://drive.google.com/file/d/1ZxDtMdMIqkGteFs5ObV0lLPbnhPdvaZR"
    }
  ],
  "zoe_admiraal": [
    {
      "datum": "2026-03-29T22:00:00.000Z",
      "titel": "Roberts houdt Tilburg in leven_ ‘De druk stond er vol op’",
      "bullet": "Haar stick raakte de 2-1 strafcorner van Roberts.",
      "link": "https://drive.google.com/file/d/1l_F_RDSAuOXvXwmihc1HNduCV6WMo9Nn"
    },
    {
      "datum": "2026-03-30T22:00:00.000Z",
      "titel": "Roberts houdt Tilburg in leven_ ‘De druk stond er vol op’",
      "bullet": "Lijnstop van HGC, via haar stick scoorde Roberts de 2-1 uit een strafcorner.",
      "link": "https://drive.google.com/file/d/1ZxDtMdMIqkGteFs5ObV0lLPbnhPdvaZR"
    }
  ],
  "iris_dominicus": [
    {
      "datum": "2026-03-29T22:00:00.000Z",
      "titel": "Roberts houdt Tilburg in leven_ ‘De druk stond er vol op’",
      "bullet": "Haar forehand variant leidde tot de 3-1 strafcorner.",
      "link": "https://drive.google.com/file/d/1l_F_RDSAuOXvXwmihc1HNduCV6WMo9Nn"
    },
    {
      "datum": "2026-03-30T22:00:00.000Z",
      "titel": "Roberts houdt Tilburg in leven_ ‘De druk stond er vol op’",
      "bullet": "Betrokken bij een strafcorner variant die leidde tot de 3-1 voorsprong.",
      "link": "https://drive.google.com/file/d/1ZxDtMdMIqkGteFs5ObV0lLPbnhPdvaZR"
    }
  ],
  "emmely_bakker": [
    {
      "datum": "2026-03-29T22:00:00.000Z",
      "titel": "Roberts houdt Tilburg in leven_ ‘De druk stond er vol op’",
      "bullet": "Maakte fraai af na een splijtende pass van Roberts.",
      "link": "https://drive.google.com/file/d/1l_F_RDSAuOXvXwmihc1HNduCV6WMo9Nn"
    },
    {
      "datum": "2026-03-30T22:00:00.000Z",
      "titel": "Roberts houdt Tilburg in leven_ ‘De druk stond er vol op’",
      "bullet": "Maakte een doelpunt na een splijtende pass van Mikki Roberts.",
      "link": "https://drive.google.com/file/d/1ZxDtMdMIqkGteFs5ObV0lLPbnhPdvaZR"
    }
  ],
  "joren_romijn": [
    {
      "datum": "2026-03-30T22:00:00.000Z",
      "titel": "Hurley weer met lege handen_ 'Waren angstig en te laf'",
      "bullet": "Keeper van Hurley, vervulde een bijzondere dubbelrol in de wedstrijd.",
      "link": "https://drive.google.com/file/d/1M2A-hLMxT52yyFPJpjnUMAwBCDptMMcD"
    },
    {
      "datum": "2026-03-30T22:00:00.000Z",
      "titel": "Hurley weer met lege handen_ 'Waren angstig en te laf'",
      "bullet": "Werd ingewisseld voor een veldspeler en coachte luidkeels vanaf de zijlijn.",
      "link": "https://drive.google.com/file/d/1M2A-hLMxT52yyFPJpjnUMAwBCDptMMcD"
    },
    {
      "datum": "2026-03-30T22:00:00.000Z",
      "titel": "Hurley weer met lege handen_ 'Waren angstig en te laf'",
      "bullet": "Zucht over de teleurstelling en het gebrek aan kansen voor Hurley.",
      "link": "https://drive.google.com/file/d/1M2A-hLMxT52yyFPJpjnUMAwBCDptMMcD"
    }
  ],
  "niels_de_joode": [
    {
      "datum": "2026-03-30T22:00:00.000Z",
      "titel": "Hurley weer met lege handen_ 'Waren angstig en te laf'",
      "bullet": "Scoorde een van de twee doelpunten voor Schaerweijde tegen Hurley.",
      "link": "https://drive.google.com/file/d/1M2A-hLMxT52yyFPJpjnUMAwBCDptMMcD"
    },
    {
      "datum": "2026-03-30T22:00:00.000Z",
      "titel": "HK (H)_ Den Bosch naar plek vier, winst Schaerweijde",
      "bullet": "Scoorde een doelpunt voor Schaerweijde.",
      "link": "https://drive.google.com/file/d/1AjHAbQi9OtFlrqPPttdgodkU-UNcxw1T"
    },
    {
      "datum": "2026-03-30T22:00:00.000Z",
      "titel": "HK (H)_ Den Bosch naar plek vier, winst Schaerweijde",
      "bullet": "Droeg bij aan de 2-1 overwinning op Hurley.",
      "link": "https://drive.google.com/file/d/1AjHAbQi9OtFlrqPPttdgodkU-UNcxw1T"
    }
  ],
  "jelle_westendorp": [
    {
      "datum": "2026-03-30T22:00:00.000Z",
      "titel": "Hurley weer met lege handen_ 'Waren angstig en te laf'",
      "bullet": "Scoorde een van de twee doelpunten voor Schaerweijde tegen Hurley.",
      "link": "https://drive.google.com/file/d/1M2A-hLMxT52yyFPJpjnUMAwBCDptMMcD"
    },
    {
      "datum": "2026-03-30T22:00:00.000Z",
      "titel": "HK (H)_ Den Bosch naar plek vier, winst Schaerweijde",
      "bullet": "Scoorde een doelpunt voor Schaerweijde.",
      "link": "https://drive.google.com/file/d/1AjHAbQi9OtFlrqPPttdgodkU-UNcxw1T"
    },
    {
      "datum": "2026-03-30T22:00:00.000Z",
      "titel": "HK (H)_ Den Bosch naar plek vier, winst Schaerweijde",
      "bullet": "Droeg bij aan de thuiszege tegen Hurley.",
      "link": "https://drive.google.com/file/d/1AjHAbQi9OtFlrqPPttdgodkU-UNcxw1T"
    }
  ],
  "pim_wasser": [
    {
      "datum": "2026-03-30T22:00:00.000Z",
      "titel": "Hurley weer met lege handen_ 'Waren angstig en te laf'",
      "bullet": "Liep een kapotte knie en gebroken vinger op tijdens de wedstrijd.",
      "link": "https://drive.google.com/file/d/1M2A-hLMxT52yyFPJpjnUMAwBCDptMMcD"
    },
    {
      "datum": "2026-03-30T22:00:00.000Z",
      "titel": "Hurley weer met lege handen_ 'Waren angstig en te laf'",
      "bullet": "Toonde strijd door zich voor corners te gooien.",
      "link": "https://drive.google.com/file/d/1M2A-hLMxT52yyFPJpjnUMAwBCDptMMcD"
    }
  ],
  "berendts": [
    {
      "datum": "2026-03-30T22:00:00.000Z",
      "titel": "Hurley weer met lege handen_ 'Waren angstig en te laf'",
      "bullet": "Maakte de late 2-1 voor Hurley in de wedstrijd tegen Schaerweijde.",
      "link": "https://drive.google.com/file/d/1M2A-hLMxT52yyFPJpjnUMAwBCDptMMcD"
    }
  ],
  "mees_loman": [
    {
      "datum": "2026-03-30T22:00:00.000Z",
      "titel": "Hurley weer met lege handen_ 'Waren angstig en te laf'",
      "bullet": "Afgebeeld luisterend naar coach Enzo Torossi samen met Hjalmar Voskuil.",
      "link": "https://drive.google.com/file/d/1M2A-hLMxT52yyFPJpjnUMAwBCDptMMcD"
    }
  ],
  "hjalmar_voskuil": [
    {
      "datum": "2026-03-30T22:00:00.000Z",
      "titel": "Hurley weer met lege handen_ 'Waren angstig en te laf'",
      "bullet": "Afgebeeld luisterend naar coach Enzo Torossi samen met Mees Loman.",
      "link": "https://drive.google.com/file/d/1M2A-hLMxT52yyFPJpjnUMAwBCDptMMcD"
    }
  ],
  "ollie_payne": [
    {
      "datum": "2026-03-30T22:00:00.000Z",
      "titel": "Hurley weer met lege handen_ 'Waren angstig en te laf'",
      "bullet": "Internationale keeper die Joren Romijn verving bij Amsterdam na zijn vertrek.",
      "link": "https://drive.google.com/file/d/1M2A-hLMxT52yyFPJpjnUMAwBCDptMMcD"
    }
  ],
  "remi_talma": [
    {
      "datum": "2026-03-30T22:00:00.000Z",
      "titel": "Roberts houdt Tilburg in leven_ ‘De druk stond er vol op’",
      "bullet": "Huidige coach van Tilburg, volgde Matias Vila op in de winterstop.",
      "link": "https://drive.google.com/file/d/1ZxDtMdMIqkGteFs5ObV0lLPbnhPdvaZR"
    },
    {
      "datum": "2026-03-30T22:00:00.000Z",
      "titel": "Roberts houdt Tilburg in leven_ ‘De druk stond er vol op’",
      "bullet": "Heeft de ploeg een duidelijke stijgende lijn laten zien.",
      "link": "https://drive.google.com/file/d/1ZxDtMdMIqkGteFs5ObV0lLPbnhPdvaZR"
    },
    {
      "datum": "2026-03-30T22:00:00.000Z",
      "titel": "Roberts houdt Tilburg in leven_ ‘De druk stond er vol op’",
      "bullet": "Bereidde zich uitstekend voor en creëerde een goede flow.",
      "link": "https://drive.google.com/file/d/1ZxDtMdMIqkGteFs5ObV0lLPbnhPdvaZR"
    }
  ],
  "matias_vila": [
    {
      "datum": "2026-03-30T22:00:00.000Z",
      "titel": "Roberts houdt Tilburg in leven_ ‘De druk stond er vol op’",
      "bullet": "Voormalig coach van Tilburg, vertrok in de winterstop.",
      "link": "https://drive.google.com/file/d/1ZxDtMdMIqkGteFs5ObV0lLPbnhPdvaZR"
    },
    {
      "datum": "2026-03-30T22:00:00.000Z",
      "titel": "Roberts houdt Tilburg in leven_ ‘De druk stond er vol op’",
      "bullet": "Ging aan de slag als video-analist bij het Indiase nationale team.",
      "link": "https://drive.google.com/file/d/1ZxDtMdMIqkGteFs5ObV0lLPbnhPdvaZR"
    }
  ],
  "margot_van_geffen": [
    {
      "datum": "2026-03-30T22:00:00.000Z",
      "titel": "Roberts houdt Tilburg in leven_ ‘De druk stond er vol op’",
      "bullet": "Assistent-trainer van Tilburg.",
      "link": "https://drive.google.com/file/d/1ZxDtMdMIqkGteFs5ObV0lLPbnhPdvaZR"
    }
  ],
  "koen_bijen": [
    {
      "datum": "2026-03-30T22:00:00.000Z",
      "titel": "HK (H)_ Den Bosch naar plek vier, winst Schaerweijde",
      "bullet": "Scoorde een doelpunt in het eerste kwart.",
      "link": "https://drive.google.com/file/d/1AjHAbQi9OtFlrqPPttdgodkU-UNcxw1T"
    },
    {
      "datum": "2026-03-30T22:00:00.000Z",
      "titel": "HK (H)_ Den Bosch naar plek vier, winst Schaerweijde",
      "bullet": "Opende de score voor Den Bosch in de 10e minuut.",
      "link": "https://drive.google.com/file/d/1AjHAbQi9OtFlrqPPttdgodkU-UNcxw1T"
    }
  ],
  "max_kreft": [
    {
      "datum": "2026-03-30T22:00:00.000Z",
      "titel": "HK (H)_ Den Bosch naar plek vier, winst Schaerweijde",
      "bullet": "Scoorde een doelpunt in het eerste kwart.",
      "link": "https://drive.google.com/file/d/1AjHAbQi9OtFlrqPPttdgodkU-UNcxw1T"
    },
    {
      "datum": "2026-03-30T22:00:00.000Z",
      "titel": "HK (H)_ Den Bosch naar plek vier, winst Schaerweijde",
      "bullet": "Ontving een groene kaart in de 43e minuut.",
      "link": "https://drive.google.com/file/d/1AjHAbQi9OtFlrqPPttdgodkU-UNcxw1T"
    }
  ],
  "teun_beins": [
    {
      "datum": "2026-03-30T22:00:00.000Z",
      "titel": "HK (H)_ Den Bosch naar plek vier, winst Schaerweijde",
      "bullet": "Verkleinde de achterstand met een strafcornerdoelpunt.",
      "link": "https://drive.google.com/file/d/1AjHAbQi9OtFlrqPPttdgodkU-UNcxw1T"
    },
    {
      "datum": "2026-03-30T22:00:00.000Z",
      "titel": "HK (H)_ Den Bosch naar plek vier, winst Schaerweijde",
      "bullet": "Clubtopscorer van Bloemendaal met 13 treffers.",
      "link": "https://drive.google.com/file/d/1AjHAbQi9OtFlrqPPttdgodkU-UNcxw1T"
    },
    {
      "datum": "2026-03-30T22:00:00.000Z",
      "titel": "HK (H)_ Den Bosch naar plek vier, winst Schaerweijde",
      "bullet": "Evenaarde zijn persoonlijk record aantal doelpunten.",
      "link": "https://drive.google.com/file/d/1AjHAbQi9OtFlrqPPttdgodkU-UNcxw1T"
    },
    {
      "datum": "2026-04-02T22:00:00.000Z",
      "titel": "Topscorers_ familie-jubileum voor zusjes Pien en Jip Dicke",
      "bullet": "Staat op 13 goals na zeventien speelronden.",
      "link": "https://drive.google.com/file/d/1aRuLl3sPlKdye7gpamhIuZZoGdHkaWYe"
    },
    {
      "datum": "2026-04-02T22:00:00.000Z",
      "titel": "Topscorers_ familie-jubileum voor zusjes Pien en Jip Dicke",
      "bullet": "Scoorde 13 strafcornerdoelpunten.",
      "link": "https://drive.google.com/file/d/1aRuLl3sPlKdye7gpamhIuZZoGdHkaWYe"
    }
  ],
  "timo_boers": [
    {
      "datum": "2026-03-30T22:00:00.000Z",
      "titel": "HK (H)_ Den Bosch naar plek vier, winst Schaerweijde",
      "bullet": "Scoorde een doelpunt uit een rake strafcorner.",
      "link": "https://drive.google.com/file/d/1AjHAbQi9OtFlrqPPttdgodkU-UNcxw1T"
    },
    {
      "datum": "2026-03-30T22:00:00.000Z",
      "titel": "HK (H)_ Den Bosch naar plek vier, winst Schaerweijde",
      "bullet": "Zijn negentiende doelpunt van het seizoen.",
      "link": "https://drive.google.com/file/d/1AjHAbQi9OtFlrqPPttdgodkU-UNcxw1T"
    },
    {
      "datum": "2026-04-02T22:00:00.000Z",
      "titel": "Topscorers_ familie-jubileum voor zusjes Pien en Jip Dicke",
      "bullet": "Staat op 19 goals na zeventien speelronden.",
      "link": "https://drive.google.com/file/d/1aRuLl3sPlKdye7gpamhIuZZoGdHkaWYe"
    },
    {
      "datum": "2026-04-02T22:00:00.000Z",
      "titel": "Topscorers_ familie-jubileum voor zusjes Pien en Jip Dicke",
      "bullet": "Scoorde 16 strafcornerdoelpunten en 3 strafbaldoelpunten.",
      "link": "https://drive.google.com/file/d/1aRuLl3sPlKdye7gpamhIuZZoGdHkaWYe"
    }
  ],
  "zachary_wallace": [
    {
      "datum": "2026-03-30T22:00:00.000Z",
      "titel": "HK (H)_ Den Bosch naar plek vier, winst Schaerweijde",
      "bullet": "Bepaalde de eindstand op 2-3 met een strafbal.",
      "link": "https://drive.google.com/file/d/1AjHAbQi9OtFlrqPPttdgodkU-UNcxw1T"
    },
    {
      "datum": "2026-03-30T22:00:00.000Z",
      "titel": "HK (H)_ Den Bosch naar plek vier, winst Schaerweijde",
      "bullet": "Scoorde een doelpunt in de slotfase van de wedstrijd.",
      "link": "https://drive.google.com/file/d/1AjHAbQi9OtFlrqPPttdgodkU-UNcxw1T"
    }
  ],
  "wiegert_schut": [
    {
      "datum": "2026-03-30T22:00:00.000Z",
      "titel": "HK (H)_ Den Bosch naar plek vier, winst Schaerweijde",
      "bullet": "Ontving een groene kaart in de 45e minuut.",
      "link": "https://drive.google.com/file/d/1AjHAbQi9OtFlrqPPttdgodkU-UNcxw1T"
    }
  ],
  "elian_mazkour": [
    {
      "datum": "2026-03-30T22:00:00.000Z",
      "titel": "HK (H)_ Den Bosch naar plek vier, winst Schaerweijde",
      "bullet": "Ontving een groene kaart in de 54e minuut.",
      "link": "https://drive.google.com/file/d/1AjHAbQi9OtFlrqPPttdgodkU-UNcxw1T"
    }
  ],
  "fred_newbold": [
    {
      "datum": "2026-03-30T22:00:00.000Z",
      "titel": "HK (H)_ Den Bosch naar plek vier, winst Schaerweijde",
      "bullet": "Ontving een groene kaart in de 34e minuut.",
      "link": "https://drive.google.com/file/d/1AjHAbQi9OtFlrqPPttdgodkU-UNcxw1T"
    }
  ],
  "nikas_berendts": [
    {
      "datum": "2026-03-30T22:00:00.000Z",
      "titel": "HK (H)_ Den Bosch naar plek vier, winst Schaerweijde",
      "bullet": "Scoorde een doelpunt uit een strafcorner.",
      "link": "https://drive.google.com/file/d/1AjHAbQi9OtFlrqPPttdgodkU-UNcxw1T"
    },
    {
      "datum": "2026-03-30T22:00:00.000Z",
      "titel": "HK (H)_ Den Bosch naar plek vier, winst Schaerweijde",
      "bullet": "Zijn doelpunt viel in de 59e minuut.",
      "link": "https://drive.google.com/file/d/1AjHAbQi9OtFlrqPPttdgodkU-UNcxw1T"
    }
  ],
  "jip_janssen": [
    {
      "datum": "2026-03-30T22:00:00.000Z",
      "titel": "HK (H)_ Den Bosch naar plek vier, winst Schaerweijde",
      "bullet": "Zette Kampong op voorsprong met een strafcorner.",
      "link": "https://drive.google.com/file/d/1AjHAbQi9OtFlrqPPttdgodkU-UNcxw1T"
    },
    {
      "datum": "2026-03-30T22:00:00.000Z",
      "titel": "HK (H)_ Den Bosch naar plek vier, winst Schaerweijde",
      "bullet": "Scoorde in de 36e minuut.",
      "link": "https://drive.google.com/file/d/1AjHAbQi9OtFlrqPPttdgodkU-UNcxw1T"
    }
  ],
  "nick_van_trigt": [
    {
      "datum": "2026-03-30T22:00:00.000Z",
      "titel": "HK (H)_ Den Bosch naar plek vier, winst Schaerweijde",
      "bullet": "Scoorde een doelpunt voor Rotterdam.",
      "link": "https://drive.google.com/file/d/1AjHAbQi9OtFlrqPPttdgodkU-UNcxw1T"
    },
    {
      "datum": "2026-03-30T22:00:00.000Z",
      "titel": "HK (H)_ Den Bosch naar plek vier, winst Schaerweijde",
      "bullet": "Droeg bij aan de overwinning op Kampong.",
      "link": "https://drive.google.com/file/d/1AjHAbQi9OtFlrqPPttdgodkU-UNcxw1T"
    }
  ],
  "tjep_hoedemakers": [
    {
      "datum": "2026-03-30T22:00:00.000Z",
      "titel": "HK (H)_ Den Bosch naar plek vier, winst Schaerweijde",
      "bullet": "Scoorde een doelpunt voor Rotterdam.",
      "link": "https://drive.google.com/file/d/1AjHAbQi9OtFlrqPPttdgodkU-UNcxw1T"
    },
    {
      "datum": "2026-03-30T22:00:00.000Z",
      "titel": "HK (H)_ Den Bosch naar plek vier, winst Schaerweijde",
      "bullet": "Droeg bij aan de vijfde competitiezege op rij.",
      "link": "https://drive.google.com/file/d/1AjHAbQi9OtFlrqPPttdgodkU-UNcxw1T"
    }
  ],
  "timme_van_der_heijden": [
    {
      "datum": "2026-03-30T22:00:00.000Z",
      "titel": "HK (H)_ Den Bosch naar plek vier, winst Schaerweijde",
      "bullet": "Scoorde een doelpunt voor Rotterdam.",
      "link": "https://drive.google.com/file/d/1AjHAbQi9OtFlrqPPttdgodkU-UNcxw1T"
    },
    {
      "datum": "2026-03-30T22:00:00.000Z",
      "titel": "HK (H)_ Den Bosch naar plek vier, winst Schaerweijde",
      "bullet": "Stelde de overwinning veilig in de 57e minuut.",
      "link": "https://drive.google.com/file/d/1AjHAbQi9OtFlrqPPttdgodkU-UNcxw1T"
    }
  ],
  "thijs_van_dam": [
    {
      "datum": "2026-03-30T22:00:00.000Z",
      "titel": "HK (H)_ Den Bosch naar plek vier, winst Schaerweijde",
      "bullet": "Ontving een groene kaart in de 13e minuut.",
      "link": "https://drive.google.com/file/d/1AjHAbQi9OtFlrqPPttdgodkU-UNcxw1T"
    }
  ],
  "derck_de_vlider": [
    {
      "datum": "2026-03-30T22:00:00.000Z",
      "titel": "HK (H)_ Den Bosch naar plek vier, winst Schaerweijde",
      "bullet": "Ontving een groene kaart in de 19e minuut.",
      "link": "https://drive.google.com/file/d/1AjHAbQi9OtFlrqPPttdgodkU-UNcxw1T"
    }
  ],
  "sander_van_de_putte": [
    {
      "datum": "2026-03-30T22:00:00.000Z",
      "titel": "HK (H)_ Den Bosch naar plek vier, winst Schaerweijde",
      "bullet": "Ontving een groene kaart in de 22e minuut.",
      "link": "https://drive.google.com/file/d/1AjHAbQi9OtFlrqPPttdgodkU-UNcxw1T"
    }
  ],
  "bouwe_buitenhuis": [
    {
      "datum": "2026-03-30T22:00:00.000Z",
      "titel": "HK (H)_ Den Bosch naar plek vier, winst Schaerweijde",
      "bullet": "Ontving een groene kaart in de 25e minuut.",
      "link": "https://drive.google.com/file/d/1AjHAbQi9OtFlrqPPttdgodkU-UNcxw1T"
    },
    {
      "datum": "2026-03-30T22:00:00.000Z",
      "titel": "HK (H)_ Den Bosch naar plek vier, winst Schaerweijde",
      "bullet": "Ontving een gele kaart in de 34e minuut.",
      "link": "https://drive.google.com/file/d/1AjHAbQi9OtFlrqPPttdgodkU-UNcxw1T"
    }
  ],
  "sam_steins_bisschop": [
    {
      "datum": "2026-03-30T22:00:00.000Z",
      "titel": "HK (H)_ Den Bosch naar plek vier, winst Schaerweijde",
      "bullet": "Zette Amsterdam op voorsprong.",
      "link": "https://drive.google.com/file/d/1AjHAbQi9OtFlrqPPttdgodkU-UNcxw1T"
    },
    {
      "datum": "2026-03-30T22:00:00.000Z",
      "titel": "HK (H)_ Den Bosch naar plek vier, winst Schaerweijde",
      "bullet": "Scoorde in de 35e minuut.",
      "link": "https://drive.google.com/file/d/1AjHAbQi9OtFlrqPPttdgodkU-UNcxw1T"
    },
    {
      "datum": "2026-03-30T22:00:00.000Z",
      "titel": "HK (H)_ Den Bosch naar plek vier, winst Schaerweijde",
      "bullet": "Ontving een groene kaart in de 25e minuut.",
      "link": "https://drive.google.com/file/d/1AjHAbQi9OtFlrqPPttdgodkU-UNcxw1T"
    }
  ],
  "tom_provily": [
    {
      "datum": "2026-03-30T22:00:00.000Z",
      "titel": "HK (H)_ Den Bosch naar plek vier, winst Schaerweijde",
      "bullet": "Scoorde een doelpunt voor HDM.",
      "link": "https://drive.google.com/file/d/1AjHAbQi9OtFlrqPPttdgodkU-UNcxw1T"
    },
    {
      "datum": "2026-03-30T22:00:00.000Z",
      "titel": "HK (H)_ Den Bosch naar plek vier, winst Schaerweijde",
      "bullet": "Zijn doelpunt viel in de 41e minuut.",
      "link": "https://drive.google.com/file/d/1AjHAbQi9OtFlrqPPttdgodkU-UNcxw1T"
    }
  ],
  "david_huussen": [
    {
      "datum": "2026-03-30T22:00:00.000Z",
      "titel": "HK (H)_ Den Bosch naar plek vier, winst Schaerweijde",
      "bullet": "Zette de thuisploeg opnieuw op voorsprong.",
      "link": "https://drive.google.com/file/d/1AjHAbQi9OtFlrqPPttdgodkU-UNcxw1T"
    },
    {
      "datum": "2026-03-30T22:00:00.000Z",
      "titel": "HK (H)_ Den Bosch naar plek vier, winst Schaerweijde",
      "bullet": "Scoorde uit een strafcorner in de 46e minuut.",
      "link": "https://drive.google.com/file/d/1AjHAbQi9OtFlrqPPttdgodkU-UNcxw1T"
    }
  ],
  "dayaan_cassiem": [
    {
      "datum": "2026-03-30T22:00:00.000Z",
      "titel": "HK (H)_ Den Bosch naar plek vier, winst Schaerweijde",
      "bullet": "Stelde de overwinning veilig met een strafcorner.",
      "link": "https://drive.google.com/file/d/1AjHAbQi9OtFlrqPPttdgodkU-UNcxw1T"
    },
    {
      "datum": "2026-03-30T22:00:00.000Z",
      "titel": "HK (H)_ Den Bosch naar plek vier, winst Schaerweijde",
      "bullet": "Scoorde in de 48e minuut.",
      "link": "https://drive.google.com/file/d/1AjHAbQi9OtFlrqPPttdgodkU-UNcxw1T"
    }
  ],
  "luke_dommershuijzen": [
    {
      "datum": "2026-03-30T22:00:00.000Z",
      "titel": "HK (H)_ Den Bosch naar plek vier, winst Schaerweijde",
      "bullet": "Stelde de overwinning veilig met een strafcorner.",
      "link": "https://drive.google.com/file/d/1AjHAbQi9OtFlrqPPttdgodkU-UNcxw1T"
    },
    {
      "datum": "2026-03-30T22:00:00.000Z",
      "titel": "HK (H)_ Den Bosch naar plek vier, winst Schaerweijde",
      "bullet": "Scoorde in de 53e minuut.",
      "link": "https://drive.google.com/file/d/1AjHAbQi9OtFlrqPPttdgodkU-UNcxw1T"
    }
  ],
  "lucas_corstens": [
    {
      "datum": "2026-03-30T22:00:00.000Z",
      "titel": "HK (H)_ Den Bosch naar plek vier, winst Schaerweijde",
      "bullet": "Ontving een groene kaart in de 29e minuut.",
      "link": "https://drive.google.com/file/d/1AjHAbQi9OtFlrqPPttdgodkU-UNcxw1T"
    }
  ],
  "chris_taberima": [
    {
      "datum": "2026-03-30T22:00:00.000Z",
      "titel": "HK (H)_ Den Bosch naar plek vier, winst Schaerweijde",
      "bullet": "Ontving een gele kaart in de 56e minuut.",
      "link": "https://drive.google.com/file/d/1AjHAbQi9OtFlrqPPttdgodkU-UNcxw1T"
    }
  ],
  "aki_kappeler": [
    {
      "datum": "2026-03-30T22:00:00.000Z",
      "titel": "HK (H)_ Den Bosch naar plek vier, winst Schaerweijde",
      "bullet": "Scoorde twee doelpunten voor Klein Zwitserland.",
      "link": "https://drive.google.com/file/d/1AjHAbQi9OtFlrqPPttdgodkU-UNcxw1T"
    },
    {
      "datum": "2026-03-30T22:00:00.000Z",
      "titel": "HK (H)_ Den Bosch naar plek vier, winst Schaerweijde",
      "bullet": "Zijn doelpunten waren beide uit een strafcorner.",
      "link": "https://drive.google.com/file/d/1AjHAbQi9OtFlrqPPttdgodkU-UNcxw1T"
    },
    {
      "datum": "2026-03-30T22:00:00.000Z",
      "titel": "Balk met gebroken teen richting WK_ 'Waggel alweer een beetje'",
      "bullet": "KZ-verdediger wiens strafcorner Lars Balk probeerde te keren.",
      "link": "https://drive.google.com/file/d/1Po0SIQjLz8X1loAijgE42NXAukbILcPW"
    }
  ],
  "willem_van_campen": [
    {
      "datum": "2026-03-30T22:00:00.000Z",
      "titel": "HK (H)_ Den Bosch naar plek vier, winst Schaerweijde",
      "bullet": "Scoorde een doelpunt voor Laren.",
      "link": "https://drive.google.com/file/d/1AjHAbQi9OtFlrqPPttdgodkU-UNcxw1T"
    },
    {
      "datum": "2026-03-30T22:00:00.000Z",
      "titel": "HK (H)_ Den Bosch naar plek vier, winst Schaerweijde",
      "bullet": "Zijn doelpunt viel in de 24e minuut.",
      "link": "https://drive.google.com/file/d/1AjHAbQi9OtFlrqPPttdgodkU-UNcxw1T"
    }
  ],
  "ties_klinkhamer": [
    {
      "datum": "2026-03-30T22:00:00.000Z",
      "titel": "HK (H)_ Den Bosch naar plek vier, winst Schaerweijde",
      "bullet": "Scoorde een doelpunt uit een strafcorner.",
      "link": "https://drive.google.com/file/d/1AjHAbQi9OtFlrqPPttdgodkU-UNcxw1T"
    },
    {
      "datum": "2026-03-30T22:00:00.000Z",
      "titel": "HK (H)_ Den Bosch naar plek vier, winst Schaerweijde",
      "bullet": "Zijn doelpunt viel in de 27e minuut.",
      "link": "https://drive.google.com/file/d/1AjHAbQi9OtFlrqPPttdgodkU-UNcxw1T"
    }
  ],
  "wout_kooijman": [
    {
      "datum": "2026-03-30T22:00:00.000Z",
      "titel": "HK (H)_ Den Bosch naar plek vier, winst Schaerweijde",
      "bullet": "Ontving een groene kaart in de 36e minuut.",
      "link": "https://drive.google.com/file/d/1AjHAbQi9OtFlrqPPttdgodkU-UNcxw1T"
    }
  ],
  "chad_futcher": [
    {
      "datum": "2026-03-30T22:00:00.000Z",
      "titel": "HK (H)_ Den Bosch naar plek vier, winst Schaerweijde",
      "bullet": "Ontving een groene kaart in de 50e minuut.",
      "link": "https://drive.google.com/file/d/1AjHAbQi9OtFlrqPPttdgodkU-UNcxw1T"
    }
  ],
  "luke_friederich": [
    {
      "datum": "2026-03-30T22:00:00.000Z",
      "titel": "HK (H)_ Den Bosch naar plek vier, winst Schaerweijde",
      "bullet": "Scoorde een doelpunt voor Klein Zwitserland.",
      "link": "https://drive.google.com/file/d/1AjHAbQi9OtFlrqPPttdgodkU-UNcxw1T"
    },
    {
      "datum": "2026-03-30T22:00:00.000Z",
      "titel": "HK (H)_ Den Bosch naar plek vier, winst Schaerweijde",
      "bullet": "Zijn doelpunt viel in de 56e minuut.",
      "link": "https://drive.google.com/file/d/1AjHAbQi9OtFlrqPPttdgodkU-UNcxw1T"
    }
  ],
  "lars_balk": [
    {
      "datum": "2026-03-30T22:00:00.000Z",
      "titel": "Balk met gebroken teen richting WK_ 'Waggel alweer een beetje'",
      "bullet": "Oranje-verdediger met teenbreuk, richt zich op Pro League-duels en WK.",
      "link": "https://drive.google.com/file/d/1Po0SIQjLz8X1loAijgE42NXAukbILcPW"
    },
    {
      "datum": "2026-03-30T22:00:00.000Z",
      "titel": "Balk met gebroken teen richting WK_ 'Waggel alweer een beetje'",
      "bullet": "Waggelt alweer een beetje en traint op hometrainer voor herstel.",
      "link": "https://drive.google.com/file/d/1Po0SIQjLz8X1loAijgE42NXAukbILcPW"
    },
    {
      "datum": "2026-03-30T22:00:00.000Z",
      "titel": "Balk met gebroken teen richting WK_ 'Waggel alweer een beetje'",
      "bullet": "Captain van Kampong, zag zijn ploeg playoff-kansen vergooien.",
      "link": "https://drive.google.com/file/d/1Po0SIQjLz8X1loAijgE42NXAukbILcPW"
    }
  ],
  "yibbi_jansen": [
    {
      "datum": "2026-04-01T22:00:00.000Z",
      "titel": "SCHC in kwartfinale EHL na cornershow en wereldgoal De Waard",
      "bullet": "Scoorde vier keer, inclusief haar eerste EHL-hattrick.",
      "link": "https://drive.google.com/file/d/1J-mpFlhhMgI3S75bhwSMnv1u_dQMqJnW"
    },
    {
      "datum": "2026-04-01T22:00:00.000Z",
      "titel": "SCHC in kwartfinale EHL na cornershow en wereldgoal De Waard",
      "bullet": "Opende de score uit een strafcorner.",
      "link": "https://drive.google.com/file/d/1J-mpFlhhMgI3S75bhwSMnv1u_dQMqJnW"
    },
    {
      "datum": "2026-04-01T22:00:00.000Z",
      "titel": "SCHC in kwartfinale EHL na cornershow en wereldgoal De Waard",
      "bullet": "Scoorde haar vierde treffer uit vijf pogingen.",
      "link": "https://drive.google.com/file/d/1J-mpFlhhMgI3S75bhwSMnv1u_dQMqJnW"
    },
    {
      "datum": "2026-04-02T22:00:00.000Z",
      "titel": "SCHC in kwartfinale EHL na cornershow en wereldgoal De Waard",
      "bullet": "Schoot vier keer raak in de wedstrijd tegen Club Egara.",
      "link": "https://drive.google.com/file/d/16MvXROg1ZpKGVgv_-medCHPXYMexUsre"
    },
    {
      "datum": "2026-04-02T22:00:00.000Z",
      "titel": "SCHC in kwartfinale EHL na cornershow en wereldgoal De Waard",
      "bullet": "Opende de score uit haar tweede strafcorner van de wedstrijd.",
      "link": "https://drive.google.com/file/d/16MvXROg1ZpKGVgv_-medCHPXYMexUsre"
    },
    {
      "datum": "2026-04-02T22:00:00.000Z",
      "titel": "SCHC in kwartfinale EHL na cornershow en wereldgoal De Waard",
      "bullet": "Maakte haar eerste hattrick ooit in de EHL met haar derde treffer.",
      "link": "https://drive.google.com/file/d/16MvXROg1ZpKGVgv_-medCHPXYMexUsre"
    },
    {
      "datum": "2026-04-02T22:00:00.000Z",
      "titel": "SCHC in kwartfinale EHL na cornershow en wereldgoal De Waard",
      "bullet": "Scoorde de 5-1 uit een strafcorner, haar vierde doelpunt van de avond.",
      "link": "https://drive.google.com/file/d/16MvXROg1ZpKGVgv_-medCHPXYMexUsre"
    },
    {
      "datum": "2026-04-02T22:00:00.000Z",
      "titel": "Topscorers_ familie-jubileum voor zusjes Pien en Jip Dicke",
      "bullet": "Is topscorer met 18 goals na zeventien speelronden.",
      "link": "https://drive.google.com/file/d/1aRuLl3sPlKdye7gpamhIuZZoGdHkaWYe"
    },
    {
      "datum": "2026-04-02T22:00:00.000Z",
      "titel": "Topscorers_ familie-jubileum voor zusjes Pien en Jip Dicke",
      "bullet": "Scoorde 2 velddoelpunten, 15 strafcornerdoelpunten en 1 strafbaldoelpunt.",
      "link": "https://drive.google.com/file/d/1aRuLl3sPlKdye7gpamhIuZZoGdHkaWYe"
    }
  ],
  "xan_de_waard": [
    {
      "datum": "2026-04-01T22:00:00.000Z",
      "titel": "SCHC in kwartfinale EHL na cornershow en wereldgoal De Waard",
      "bullet": "Produceerde een parel van een doelpunt.",
      "link": "https://drive.google.com/file/d/1J-mpFlhhMgI3S75bhwSMnv1u_dQMqJnW"
    },
    {
      "datum": "2026-04-01T22:00:00.000Z",
      "titel": "SCHC in kwartfinale EHL na cornershow en wereldgoal De Waard",
      "bullet": "Rondde een vijftig meter solorun af met een push.",
      "link": "https://drive.google.com/file/d/1J-mpFlhhMgI3S75bhwSMnv1u_dQMqJnW"
    },
    {
      "datum": "2026-04-02T22:00:00.000Z",
      "titel": "SCHC in kwartfinale EHL na cornershow en wereldgoal De Waard",
      "bullet": "Produceerde een parel van een doelpunt voor SCHC.",
      "link": "https://drive.google.com/file/d/16MvXROg1ZpKGVgv_-medCHPXYMexUsre"
    },
    {
      "datum": "2026-04-02T22:00:00.000Z",
      "titel": "SCHC in kwartfinale EHL na cornershow en wereldgoal De Waard",
      "bullet": "Rondde een solorun van vijftig meter af met een push in de lange hoek.",
      "link": "https://drive.google.com/file/d/16MvXROg1ZpKGVgv_-medCHPXYMexUsre"
    },
    {
      "datum": "2026-04-02T22:00:00.000Z",
      "titel": "SCHC in kwartfinale EHL na cornershow en wereldgoal De Waard",
      "bullet": "Scoorde de 3-0 voor SCHC.",
      "link": "https://drive.google.com/file/d/16MvXROg1ZpKGVgv_-medCHPXYMexUsre"
    }
  ],
  "mariona_girabent": [
    {
      "datum": "2026-04-01T22:00:00.000Z",
      "titel": "SCHC in kwartfinale EHL na cornershow en wereldgoal De Waard",
      "bullet": "Keeper van de Spaanse debutant Club Egara.",
      "link": "https://drive.google.com/file/d/1J-mpFlhhMgI3S75bhwSMnv1u_dQMqJnW"
    },
    {
      "datum": "2026-04-01T22:00:00.000Z",
      "titel": "SCHC in kwartfinale EHL na cornershow en wereldgoal De Waard",
      "bullet": "Kreeg meerdere strafcorners en doelpunten tegen.",
      "link": "https://drive.google.com/file/d/1J-mpFlhhMgI3S75bhwSMnv1u_dQMqJnW"
    }
  ],
  "jip_dicke": [
    {
      "datum": "2026-04-01T22:00:00.000Z",
      "titel": "SCHC in kwartfinale EHL na cornershow en wereldgoal De Waard",
      "bullet": "Kwam in de buurt van de Spaanse keeper.",
      "link": "https://drive.google.com/file/d/1J-mpFlhhMgI3S75bhwSMnv1u_dQMqJnW"
    },
    {
      "datum": "2026-04-01T22:00:00.000Z",
      "titel": "SCHC in kwartfinale EHL na cornershow en wereldgoal De Waard",
      "bullet": "Scoorde de 6-1 uit een strafcornerrebound.",
      "link": "https://drive.google.com/file/d/1J-mpFlhhMgI3S75bhwSMnv1u_dQMqJnW"
    },
    {
      "datum": "2026-04-01T22:00:00.000Z",
      "titel": "SCHC in kwartfinale EHL na cornershow en wereldgoal De Waard",
      "bullet": "Haar eerste EHL-doelpunt ooit.",
      "link": "https://drive.google.com/file/d/1J-mpFlhhMgI3S75bhwSMnv1u_dQMqJnW"
    },
    {
      "datum": "2026-04-02T22:00:00.000Z",
      "titel": "SCHC in kwartfinale EHL na cornershow en wereldgoal De Waard",
      "bullet": "Kwam één keer in de buurt van de Spaanse keeper Mariona Girabent.",
      "link": "https://drive.google.com/file/d/16MvXROg1ZpKGVgv_-medCHPXYMexUsre"
    },
    {
      "datum": "2026-04-02T22:00:00.000Z",
      "titel": "SCHC in kwartfinale EHL na cornershow en wereldgoal De Waard",
      "bullet": "Scoorde de 6-1 uit een strafcornerrebound in het laatste kwart.",
      "link": "https://drive.google.com/file/d/16MvXROg1ZpKGVgv_-medCHPXYMexUsre"
    },
    {
      "datum": "2026-04-02T22:00:00.000Z",
      "titel": "SCHC in kwartfinale EHL na cornershow en wereldgoal De Waard",
      "bullet": "Maakte haar eerste doelpunt ooit in de EHL.",
      "link": "https://drive.google.com/file/d/16MvXROg1ZpKGVgv_-medCHPXYMexUsre"
    },
    {
      "datum": "2026-04-02T22:00:00.000Z",
      "titel": "Topscorers_ familie-jubileum voor zusjes Pien en Jip Dicke",
      "bullet": "Tipte de gelijkmaker binnen uit een strafcornervariant tegen Kampong.",
      "link": "https://drive.google.com/file/d/1aRuLl3sPlKdye7gpamhIuZZoGdHkaWYe"
    },
    {
      "datum": "2026-04-02T22:00:00.000Z",
      "titel": "Topscorers_ familie-jubileum voor zusjes Pien en Jip Dicke",
      "bullet": "Bereikte samen met Pien 150 doelpunten in de Hoofdklasse.",
      "link": "https://drive.google.com/file/d/1aRuLl3sPlKdye7gpamhIuZZoGdHkaWYe"
    },
    {
      "datum": "2026-04-02T22:00:00.000Z",
      "titel": "Topscorers_ familie-jubileum voor zusjes Pien en Jip Dicke",
      "bullet": "Scoorde haar zeventiende goal van het seizoen.",
      "link": "https://drive.google.com/file/d/1aRuLl3sPlKdye7gpamhIuZZoGdHkaWYe"
    }
  ],
  "mette_winter": [
    {
      "datum": "2026-04-01T22:00:00.000Z",
      "titel": "SCHC in kwartfinale EHL na cornershow en wereldgoal De Waard",
      "bullet": "Kwam één keer in de buurt van de Spaanse keeper.",
      "link": "https://drive.google.com/file/d/1J-mpFlhhMgI3S75bhwSMnv1u_dQMqJnW"
    },
    {
      "datum": "2026-04-02T22:00:00.000Z",
      "titel": "SCHC in kwartfinale EHL na cornershow en wereldgoal De Waard",
      "bullet": "Kwam één keer in de buurt van de Spaanse keeper Mariona Girabent.",
      "link": "https://drive.google.com/file/d/16MvXROg1ZpKGVgv_-medCHPXYMexUsre"
    }
  ],
  "marsha_zwezereijn": [
    {
      "datum": "2026-04-01T22:00:00.000Z",
      "titel": "SCHC in kwartfinale EHL na cornershow en wereldgoal De Waard",
      "bullet": "SCHC-keeper.",
      "link": "https://drive.google.com/file/d/1J-mpFlhhMgI3S75bhwSMnv1u_dQMqJnW"
    },
    {
      "datum": "2026-04-01T22:00:00.000Z",
      "titel": "SCHC in kwartfinale EHL na cornershow en wereldgoal De Waard",
      "bullet": "Had weinig te doen in de eerste dertig minuten.",
      "link": "https://drive.google.com/file/d/1J-mpFlhhMgI3S75bhwSMnv1u_dQMqJnW"
    },
    {
      "datum": "2026-04-01T22:00:00.000Z",
      "titel": "SCHC in kwartfinale EHL na cornershow en wereldgoal De Waard",
      "bullet": "Werd drie minuten voor tijd vervangen.",
      "link": "https://drive.google.com/file/d/1J-mpFlhhMgI3S75bhwSMnv1u_dQMqJnW"
    },
    {
      "datum": "2026-04-02T22:00:00.000Z",
      "titel": "SCHC in kwartfinale EHL na cornershow en wereldgoal De Waard",
      "bullet": "Had een rustige eerste dertig minuten, de Spaanse vrouwen kwamen nauwelijks in haar buurt.",
      "link": "https://drive.google.com/file/d/16MvXROg1ZpKGVgv_-medCHPXYMexUsre"
    },
    {
      "datum": "2026-04-02T22:00:00.000Z",
      "titel": "SCHC in kwartfinale EHL na cornershow en wereldgoal De Waard",
      "bullet": "Werd drie minuten voor tijd vervangen door reservekeeper Rifka Bakker.",
      "link": "https://drive.google.com/file/d/16MvXROg1ZpKGVgv_-medCHPXYMexUsre"
    }
  ],
  "natalia_vilanova": [
    {
      "datum": "2026-04-01T22:00:00.000Z",
      "titel": "SCHC in kwartfinale EHL na cornershow en wereldgoal De Waard",
      "bullet": "Scoorde de Spaanse treffer.",
      "link": "https://drive.google.com/file/d/1J-mpFlhhMgI3S75bhwSMnv1u_dQMqJnW"
    },
    {
      "datum": "2026-04-01T22:00:00.000Z",
      "titel": "SCHC in kwartfinale EHL na cornershow en wereldgoal De Waard",
      "bullet": "Promoveerde een assist van Mitajvila tot doelpunt.",
      "link": "https://drive.google.com/file/d/1J-mpFlhhMgI3S75bhwSMnv1u_dQMqJnW"
    }
  ],
  "marta_mitajvila": [
    {
      "datum": "2026-04-01T22:00:00.000Z",
      "titel": "SCHC in kwartfinale EHL na cornershow en wereldgoal De Waard",
      "bullet": "Gaf een assist voor de Spaanse treffer.",
      "link": "https://drive.google.com/file/d/1J-mpFlhhMgI3S75bhwSMnv1u_dQMqJnW"
    }
  ],
  "lotte_ruts": [
    {
      "datum": "2026-04-01T22:00:00.000Z",
      "titel": "SCHC in kwartfinale EHL na cornershow en wereldgoal De Waard",
      "bullet": "Forceerde de vierde strafcorner van de wedstrijd.",
      "link": "https://drive.google.com/file/d/1J-mpFlhhMgI3S75bhwSMnv1u_dQMqJnW"
    },
    {
      "datum": "2026-04-02T22:00:00.000Z",
      "titel": "SCHC in kwartfinale EHL na cornershow en wereldgoal De Waard",
      "bullet": "Forceerde de vierde strafcorner van de wedstrijd met een individuele actie.",
      "link": "https://drive.google.com/file/d/16MvXROg1ZpKGVgv_-medCHPXYMexUsre"
    }
  ],
  "pien_dicke": [
    {
      "datum": "2026-04-01T22:00:00.000Z",
      "titel": "SCHC in kwartfinale EHL na cornershow en wereldgoal De Waard",
      "bullet": "Forceerde een nieuwe strafcorner.",
      "link": "https://drive.google.com/file/d/1J-mpFlhhMgI3S75bhwSMnv1u_dQMqJnW"
    },
    {
      "datum": "2026-04-02T22:00:00.000Z",
      "titel": "SCHC in kwartfinale EHL na cornershow en wereldgoal De Waard",
      "bullet": "Forceerde een nieuwe strafcorner in het restant van de wedstrijd.",
      "link": "https://drive.google.com/file/d/16MvXROg1ZpKGVgv_-medCHPXYMexUsre"
    },
    {
      "datum": "2026-04-02T22:00:00.000Z",
      "titel": "Topscorers_ familie-jubileum voor zusjes Pien en Jip Dicke",
      "bullet": "Scoorde de 1-2 tegen Kampong na een 0-2 achterstand.",
      "link": "https://drive.google.com/file/d/1aRuLl3sPlKdye7gpamhIuZZoGdHkaWYe"
    },
    {
      "datum": "2026-04-02T22:00:00.000Z",
      "titel": "Topscorers_ familie-jubileum voor zusjes Pien en Jip Dicke",
      "bullet": "Bereikte samen met Jip 150 doelpunten in de Hoofdklasse.",
      "link": "https://drive.google.com/file/d/1aRuLl3sPlKdye7gpamhIuZZoGdHkaWYe"
    },
    {
      "datum": "2026-04-02T22:00:00.000Z",
      "titel": "Topscorers_ familie-jubileum voor zusjes Pien en Jip Dicke",
      "bullet": "Scoorde tot nu toe 85 keer, waarvan 76 voor SCHC.",
      "link": "https://drive.google.com/file/d/1aRuLl3sPlKdye7gpamhIuZZoGdHkaWYe"
    }
  ],
  "rifka_bakker": [
    {
      "datum": "2026-04-01T22:00:00.000Z",
      "titel": "SCHC in kwartfinale EHL na cornershow en wereldgoal De Waard",
      "bullet": "Jonge reservekeeper.",
      "link": "https://drive.google.com/file/d/1J-mpFlhhMgI3S75bhwSMnv1u_dQMqJnW"
    },
    {
      "datum": "2026-04-01T22:00:00.000Z",
      "titel": "SCHC in kwartfinale EHL na cornershow en wereldgoal De Waard",
      "bullet": "Verving Zwezereijn drie minuten voor tijd.",
      "link": "https://drive.google.com/file/d/1J-mpFlhhMgI3S75bhwSMnv1u_dQMqJnW"
    },
    {
      "datum": "2026-04-02T22:00:00.000Z",
      "titel": "SCHC in kwartfinale EHL na cornershow en wereldgoal De Waard",
      "bullet": "Viel drie minuten voor tijd in als jonge reservekeeper.",
      "link": "https://drive.google.com/file/d/16MvXROg1ZpKGVgv_-medCHPXYMexUsre"
    },
    {
      "datum": "2026-04-02T22:00:00.000Z",
      "titel": "SCHC in kwartfinale EHL na cornershow en wereldgoal De Waard",
      "bullet": "Verving collega Zwezereijn onder de lat.",
      "link": "https://drive.google.com/file/d/16MvXROg1ZpKGVgv_-medCHPXYMexUsre"
    }
  ],
  "teuntje_de_wit": [
    {
      "datum": "2026-04-02T22:00:00.000Z",
      "titel": "Teuntje de Wit_ 'Laat mij voorin maar de vuile meters maken'",
      "bullet": "Aanvaller van Den Bosch, scoorde 2-0 en assisteerde 1-0 tegen Watsonians.",
      "link": "https://drive.google.com/file/d/1w5_GBWeNNtCC18NMIhQvyV3aGmqWq4bB"
    },
    {
      "datum": "2026-04-02T22:00:00.000Z",
      "titel": "Teuntje de Wit_ 'Laat mij voorin maar de vuile meters maken'",
      "bullet": "Maakt graag 'vuile meters' voorin, maar pikt ook graag een doelpunt mee.",
      "link": "https://drive.google.com/file/d/1w5_GBWeNNtCC18NMIhQvyV3aGmqWq4bB"
    },
    {
      "datum": "2026-04-02T22:00:00.000Z",
      "titel": "Teuntje de Wit_ 'Laat mij voorin maar de vuile meters maken'",
      "bullet": "Leert veel van teamgenoot Frédérique Matla over posities en tactiek.",
      "link": "https://drive.google.com/file/d/1w5_GBWeNNtCC18NMIhQvyV3aGmqWq4bB"
    }
  ],
  "frederique_matla": [
    {
      "datum": "2026-04-02T22:00:00.000Z",
      "titel": "Teuntje de Wit_ 'Laat mij voorin maar de vuile meters maken'",
      "bullet": "Scoorde vijf van de zes Bossche treffers tegen Watsonians, evenaarde haar EHL-record.",
      "link": "https://drive.google.com/file/d/1w5_GBWeNNtCC18NMIhQvyV3aGmqWq4bB"
    },
    {
      "datum": "2026-04-02T22:00:00.000Z",
      "titel": "Teuntje de Wit_ 'Laat mij voorin maar de vuile meters maken'",
      "bullet": "Behoort tot de meest dodelijke aanvallers van Europa, zeer scherp in de cirkel.",
      "link": "https://drive.google.com/file/d/1w5_GBWeNNtCC18NMIhQvyV3aGmqWq4bB"
    },
    {
      "datum": "2026-04-02T22:00:00.000Z",
      "titel": "Teuntje de Wit_ 'Laat mij voorin maar de vuile meters maken'",
      "bullet": "Helpt teamgenoten tactisch en met positionering, een waardevolle mentor.",
      "link": "https://drive.google.com/file/d/1w5_GBWeNNtCC18NMIhQvyV3aGmqWq4bB"
    },
    {
      "datum": "2026-04-02T22:00:00.000Z",
      "titel": "Topscorers_ familie-jubileum voor zusjes Pien en Jip Dicke",
      "bullet": "Staat op 15 goals na zeventien speelronden.",
      "link": "https://drive.google.com/file/d/1aRuLl3sPlKdye7gpamhIuZZoGdHkaWYe"
    },
    {
      "datum": "2026-04-02T22:00:00.000Z",
      "titel": "Topscorers_ familie-jubileum voor zusjes Pien en Jip Dicke",
      "bullet": "Scoorde 5 velddoelpunten, 8 strafcornerdoelpunten en 2 strafbaldoelpunten.",
      "link": "https://drive.google.com/file/d/1aRuLl3sPlKdye7gpamhIuZZoGdHkaWYe"
    }
  ],
  "joosje_burg": [
    {
      "datum": "2026-04-02T22:00:00.000Z",
      "titel": "Teuntje de Wit_ 'Laat mij voorin maar de vuile meters maken'",
      "bullet": "Oranje-international en teamgenoot van Teuntje de Wit bij Den Bosch.",
      "link": "https://drive.google.com/file/d/1w5_GBWeNNtCC18NMIhQvyV3aGmqWq4bB"
    },
    {
      "datum": "2026-04-02T22:00:00.000Z",
      "titel": "Topscorers_ familie-jubileum voor zusjes Pien en Jip Dicke",
      "bullet": "Staat op 10 goals na zeventien speelronden.",
      "link": "https://drive.google.com/file/d/1aRuLl3sPlKdye7gpamhIuZZoGdHkaWYe"
    },
    {
      "datum": "2026-04-02T22:00:00.000Z",
      "titel": "Topscorers_ familie-jubileum voor zusjes Pien en Jip Dicke",
      "bullet": "Scoorde 10 velddoelpunten.",
      "link": "https://drive.google.com/file/d/1aRuLl3sPlKdye7gpamhIuZZoGdHkaWYe"
    }
  ],
  "emily_dark": [
    {
      "datum": "2026-04-02T22:00:00.000Z",
      "titel": "Teuntje de Wit_ 'Laat mij voorin maar de vuile meters maken'",
      "bullet": "Speelde voor Watsonians in het duel tegen Den Bosch.",
      "link": "https://drive.google.com/file/d/1w5_GBWeNNtCC18NMIhQvyV3aGmqWq4bB"
    }
  ],
  "bente_van_der_veldt": [
    {
      "datum": "2026-04-02T22:00:00.000Z",
      "titel": "Van der Veldt_ van studentenleven naar officieus Oranje-debuut",
      "bullet": "Was 25 jaar, de oudste nieuweling in de Oranje-selectie.",
      "link": "https://drive.google.com/file/d/1qe4al8B5HpzhVogNuShgNX2uGDp5_cY9"
    },
    {
      "datum": "2026-04-02T22:00:00.000Z",
      "titel": "Van der Veldt_ van studentenleven naar officieus Oranje-debuut",
      "bullet": "Gaf een assist op Fay van der Elst, waardoor de score 1-2 werd.",
      "link": "https://drive.google.com/file/d/1qe4al8B5HpzhVogNuShgNX2uGDp5_cY9"
    },
    {
      "datum": "2026-04-02T22:00:00.000Z",
      "titel": "Van der Veldt_ van studentenleven naar officieus Oranje-debuut",
      "bullet": "Droeg rugnummer 38 tijdens haar officieuze debuut.",
      "link": "https://drive.google.com/file/d/1qe4al8B5HpzhVogNuShgNX2uGDp5_cY9"
    }
  ],
  "fay_van_der_elst": [
    {
      "datum": "2026-04-02T22:00:00.000Z",
      "titel": "Van der Veldt_ van studentenleven naar officieus Oranje-debuut",
      "bullet": "Scoorde een doelpunt na een assist van Bente van der Veldt.",
      "link": "https://drive.google.com/file/d/1qe4al8B5HpzhVogNuShgNX2uGDp5_cY9"
    },
    {
      "datum": "2026-04-02T22:00:00.000Z",
      "titel": "Van der Veldt_ van studentenleven naar officieus Oranje-debuut",
      "bullet": "Haar doelpunt bracht Oranje terug tot een 1-2 stand.",
      "link": "https://drive.google.com/file/d/1qe4al8B5HpzhVogNuShgNX2uGDp5_cY9"
    }
  ],
  "noa_muller": [
    {
      "datum": "2026-04-02T22:00:00.000Z",
      "titel": "Van der Veldt_ van studentenleven naar officieus Oranje-debuut",
      "bullet": "Was woensdagavond een nieuwe speler in Oranje.",
      "link": "https://drive.google.com/file/d/1qe4al8B5HpzhVogNuShgNX2uGDp5_cY9"
    }
  ],
  "fleur_wolfert": [
    {
      "datum": "2026-04-02T22:00:00.000Z",
      "titel": "Van der Veldt_ van studentenleven naar officieus Oranje-debuut",
      "bullet": "Was woensdagavond een nieuwe speler in Oranje.",
      "link": "https://drive.google.com/file/d/1qe4al8B5HpzhVogNuShgNX2uGDp5_cY9"
    }
  ],
  "veere_ter_horst": [
    {
      "datum": "2026-04-02T22:00:00.000Z",
      "titel": "Van der Veldt_ van studentenleven naar officieus Oranje-debuut",
      "bullet": "Was woensdagavond een nieuwe speler in Oranje.",
      "link": "https://drive.google.com/file/d/1qe4al8B5HpzhVogNuShgNX2uGDp5_cY9"
    }
  ],
  "iris_de_kemp": [
    {
      "datum": "2026-04-02T22:00:00.000Z",
      "titel": "Van der Veldt_ van studentenleven naar officieus Oranje-debuut",
      "bullet": "Was woensdagavond een nieuwe speler in Oranje.",
      "link": "https://drive.google.com/file/d/1qe4al8B5HpzhVogNuShgNX2uGDp5_cY9"
    }
  ],
  "sam_luttmer": [
    {
      "datum": "2026-04-02T22:00:00.000Z",
      "titel": "Van der Veldt_ van studentenleven naar officieus Oranje-debuut",
      "bullet": "Was woensdagavond een nieuwe speler in Oranje.",
      "link": "https://drive.google.com/file/d/1qe4al8B5HpzhVogNuShgNX2uGDp5_cY9"
    }
  ],
  "ivy_tellier": [
    {
      "datum": "2026-04-02T22:00:00.000Z",
      "titel": "Van der Veldt_ van studentenleven naar officieus Oranje-debuut",
      "bullet": "Was woensdagavond een nieuwe speler in Oranje.",
      "link": "https://drive.google.com/file/d/1qe4al8B5HpzhVogNuShgNX2uGDp5_cY9"
    }
  ],
  "struan_walker": [
    {
      "datum": "2026-04-02T22:00:00.000Z",
      "titel": "Topscorers_ familie-jubileum voor zusjes Pien en Jip Dicke",
      "bullet": "Maakte zijn derde hattrick van het seizoen.",
      "link": "https://drive.google.com/file/d/1aRuLl3sPlKdye7gpamhIuZZoGdHkaWYe"
    },
    {
      "datum": "2026-04-02T22:00:00.000Z",
      "titel": "Topscorers_ familie-jubileum voor zusjes Pien en Jip Dicke",
      "bullet": "Scoorde drie van de zes treffers in de 1-6 zege tegen Pinoké.",
      "link": "https://drive.google.com/file/d/1aRuLl3sPlKdye7gpamhIuZZoGdHkaWYe"
    },
    {
      "datum": "2026-04-02T22:00:00.000Z",
      "titel": "Topscorers_ familie-jubileum voor zusjes Pien en Jip Dicke",
      "bullet": "Voerde zijn productie op naar 22 doelpunten.",
      "link": "https://drive.google.com/file/d/1aRuLl3sPlKdye7gpamhIuZZoGdHkaWYe"
    }
  ],
  "imke_verstraeten": [
    {
      "datum": "2026-04-02T22:00:00.000Z",
      "titel": "Topscorers_ familie-jubileum voor zusjes Pien en Jip Dicke",
      "bullet": "Staat op 13 goals na zeventien speelronden.",
      "link": "https://drive.google.com/file/d/1aRuLl3sPlKdye7gpamhIuZZoGdHkaWYe"
    },
    {
      "datum": "2026-04-02T22:00:00.000Z",
      "titel": "Topscorers_ familie-jubileum voor zusjes Pien en Jip Dicke",
      "bullet": "Scoorde 9 strafcornerdoelpunten en 4 strafbaldoelpunten.",
      "link": "https://drive.google.com/file/d/1aRuLl3sPlKdye7gpamhIuZZoGdHkaWYe"
    }
  ],
  "trijntje_beljaars": [
    {
      "datum": "2026-04-02T22:00:00.000Z",
      "titel": "Topscorers_ familie-jubileum voor zusjes Pien en Jip Dicke",
      "bullet": "Staat op 11 goals na zeventien speelronden.",
      "link": "https://drive.google.com/file/d/1aRuLl3sPlKdye7gpamhIuZZoGdHkaWYe"
    },
    {
      "datum": "2026-04-02T22:00:00.000Z",
      "titel": "Topscorers_ familie-jubileum voor zusjes Pien en Jip Dicke",
      "bullet": "Scoorde 9 velddoelpunten en 2 strafcornerdoelpunten.",
      "link": "https://drive.google.com/file/d/1aRuLl3sPlKdye7gpamhIuZZoGdHkaWYe"
    }
  ],
  "lana_kalse": [
    {
      "datum": "2026-04-02T22:00:00.000Z",
      "titel": "Topscorers_ familie-jubileum voor zusjes Pien en Jip Dicke",
      "bullet": "Staat op 11 goals na zeventien speelronden.",
      "link": "https://drive.google.com/file/d/1aRuLl3sPlKdye7gpamhIuZZoGdHkaWYe"
    },
    {
      "datum": "2026-04-02T22:00:00.000Z",
      "titel": "Topscorers_ familie-jubileum voor zusjes Pien en Jip Dicke",
      "bullet": "Scoorde 9 velddoelpunten en 2 strafcornerdoelpunten.",
      "link": "https://drive.google.com/file/d/1aRuLl3sPlKdye7gpamhIuZZoGdHkaWYe"
    }
  ],
  "mink_van_der_weerden": [
    {
      "datum": "2026-04-02T22:00:00.000Z",
      "titel": "Topscorers_ familie-jubileum voor zusjes Pien en Jip Dicke",
      "bullet": "Scoorde 24 doelpunten in seizoen 2017-2018.",
      "link": "https://drive.google.com/file/d/1aRuLl3sPlKdye7gpamhIuZZoGdHkaWYe"
    },
    {
      "datum": "2026-04-02T22:00:00.000Z",
      "titel": "Topscorers_ familie-jubileum voor zusjes Pien en Jip Dicke",
      "bullet": "Zette een ongeëvenaarde prestatie neer als strafcornerkanon.",
      "link": "https://drive.google.com/file/d/1aRuLl3sPlKdye7gpamhIuZZoGdHkaWYe"
    }
  ],
  "boris_burkhardt": [
    {
      "datum": "2026-04-02T22:00:00.000Z",
      "titel": "Topscorers_ familie-jubileum voor zusjes Pien en Jip Dicke",
      "bullet": "Staat op 18 goals na zeventien speelronden.",
      "link": "https://drive.google.com/file/d/1aRuLl3sPlKdye7gpamhIuZZoGdHkaWYe"
    },
    {
      "datum": "2026-04-02T22:00:00.000Z",
      "titel": "Topscorers_ familie-jubileum voor zusjes Pien en Jip Dicke",
      "bullet": "Scoorde 8 velddoelpunten, 8 strafcornerdoelpunten en 2 strafbaldoelpunten.",
      "link": "https://drive.google.com/file/d/1aRuLl3sPlKdye7gpamhIuZZoGdHkaWYe"
    }
  ],
  "joep_troost": [
    {
      "datum": "2026-04-02T22:00:00.000Z",
      "titel": "Topscorers_ familie-jubileum voor zusjes Pien en Jip Dicke",
      "bullet": "Staat op 17 goals na zeventien speelronden.",
      "link": "https://drive.google.com/file/d/1aRuLl3sPlKdye7gpamhIuZZoGdHkaWYe"
    },
    {
      "datum": "2026-04-02T22:00:00.000Z",
      "titel": "Topscorers_ familie-jubileum voor zusjes Pien en Jip Dicke",
      "bullet": "Scoorde 4 velddoelpunten, 12 strafcornerdoelpunten en 1 strafbaldoelpunt.",
      "link": "https://drive.google.com/file/d/1aRuLl3sPlKdye7gpamhIuZZoGdHkaWYe"
    }
  ],
  "miles_bukkens": [
    {
      "datum": "2026-04-02T22:00:00.000Z",
      "titel": "Topscorers_ familie-jubileum voor zusjes Pien en Jip Dicke",
      "bullet": "Staat op 14 goals na zeventien speelronden.",
      "link": "https://drive.google.com/file/d/1aRuLl3sPlKdye7gpamhIuZZoGdHkaWYe"
    },
    {
      "datum": "2026-04-02T22:00:00.000Z",
      "titel": "Topscorers_ familie-jubileum voor zusjes Pien en Jip Dicke",
      "bullet": "Scoorde 6 velddoelpunten en 8 strafcornerdoelpunten.",
      "link": "https://drive.google.com/file/d/1aRuLl3sPlKdye7gpamhIuZZoGdHkaWYe"
    }
  ],
  "pepijn_van_der_heijden": [
    {
      "datum": "2026-04-02T22:00:00.000Z",
      "titel": "Topscorers_ familie-jubileum voor zusjes Pien en Jip Dicke",
      "bullet": "Staat op 14 goals na zeventien speelronden.",
      "link": "https://drive.google.com/file/d/1aRuLl3sPlKdye7gpamhIuZZoGdHkaWYe"
    },
    {
      "datum": "2026-04-02T22:00:00.000Z",
      "titel": "Topscorers_ familie-jubileum voor zusjes Pien en Jip Dicke",
      "bullet": "Scoorde 11 strafcornerdoelpunten en 3 strafbaldoelpunten.",
      "link": "https://drive.google.com/file/d/1aRuLl3sPlKdye7gpamhIuZZoGdHkaWYe"
    }
  ],
  "maren_eertink": [
    {
      "datum": "2026-04-02T22:00:00.000Z",
      "titel": "Topscorers_ familie-jubileum voor zusjes Pien en Jip Dicke",
      "bullet": "Scoorde één doelpunt tegen Leonidas in een 4-1 zege.",
      "link": "https://drive.google.com/file/d/1aRuLl3sPlKdye7gpamhIuZZoGdHkaWYe"
    },
    {
      "datum": "2026-04-02T22:00:00.000Z",
      "titel": "Topscorers_ familie-jubileum voor zusjes Pien en Jip Dicke",
      "bullet": "Staat op elf treffers dit seizoen.",
      "link": "https://drive.google.com/file/d/1aRuLl3sPlKdye7gpamhIuZZoGdHkaWYe"
    }
  ],
  "aafke_schrievers": [
    {
      "datum": "2026-04-02T22:00:00.000Z",
      "titel": "Topscorers_ familie-jubileum voor zusjes Pien en Jip Dicke",
      "bullet": "Staat op elf treffers dit seizoen.",
      "link": "https://drive.google.com/file/d/1aRuLl3sPlKdye7gpamhIuZZoGdHkaWYe"
    },
    {
      "datum": "2026-04-02T22:00:00.000Z",
      "titel": "Topscorers_ familie-jubileum voor zusjes Pien en Jip Dicke",
      "bullet": "Is twee goals verwijderd van lijstaanvoerder Claire Moerman.",
      "link": "https://drive.google.com/file/d/1aRuLl3sPlKdye7gpamhIuZZoGdHkaWYe"
    }
  ],
  "claire_moerman": [
    {
      "datum": "2026-04-02T22:00:00.000Z",
      "titel": "Topscorers_ familie-jubileum voor zusjes Pien en Jip Dicke",
      "bullet": "Is lijstaanvoerder met 13 goals in de Promotieklasse Dames.",
      "link": "https://drive.google.com/file/d/1aRuLl3sPlKdye7gpamhIuZZoGdHkaWYe"
    }
  ],
  "donna_dupuis": [
    {
      "datum": "2026-04-02T22:00:00.000Z",
      "titel": "Topscorers_ familie-jubileum voor zusjes Pien en Jip Dicke",
      "bullet": "Scoorde twee goals voor Victoria.",
      "link": "https://drive.google.com/file/d/1aRuLl3sPlKdye7gpamhIuZZoGdHkaWYe"
    },
    {
      "datum": "2026-04-02T22:00:00.000Z",
      "titel": "Topscorers_ familie-jubileum voor zusjes Pien en Jip Dicke",
      "bullet": "Staat op negen doelpunten.",
      "link": "https://drive.google.com/file/d/1aRuLl3sPlKdye7gpamhIuZZoGdHkaWYe"
    }
  ],
  "freeke_van_dongen": [
    {
      "datum": "2026-04-02T22:00:00.000Z",
      "titel": "Topscorers_ familie-jubileum voor zusjes Pien en Jip Dicke",
      "bullet": "Scoorde één goal namens Push.",
      "link": "https://drive.google.com/file/d/1aRuLl3sPlKdye7gpamhIuZZoGdHkaWYe"
    },
    {
      "datum": "2026-04-02T22:00:00.000Z",
      "titel": "Topscorers_ familie-jubileum voor zusjes Pien en Jip Dicke",
      "bullet": "Staat op negen doelpunten.",
      "link": "https://drive.google.com/file/d/1aRuLl3sPlKdye7gpamhIuZZoGdHkaWYe"
    }
  ],
  "anouk_gommers": [
    {
      "datum": "2026-04-02T22:00:00.000Z",
      "titel": "Topscorers_ familie-jubileum voor zusjes Pien en Jip Dicke",
      "bullet": "Staat op 9 goals na vijftien speelronden.",
      "link": "https://drive.google.com/file/d/1aRuLl3sPlKdye7gpamhIuZZoGdHkaWYe"
    }
  ],
  "helen_jacobs": [
    {
      "datum": "2026-04-02T22:00:00.000Z",
      "titel": "Topscorers_ familie-jubileum voor zusjes Pien en Jip Dicke",
      "bullet": "Staat op 7 goals na vijftien speelronden.",
      "link": "https://drive.google.com/file/d/1aRuLl3sPlKdye7gpamhIuZZoGdHkaWYe"
    }
  ],
  "fleur_gort": [
    {
      "datum": "2026-04-02T22:00:00.000Z",
      "titel": "Topscorers_ familie-jubileum voor zusjes Pien en Jip Dicke",
      "bullet": "Staat op 7 goals na vijftien speelronden.",
      "link": "https://drive.google.com/file/d/1aRuLl3sPlKdye7gpamhIuZZoGdHkaWYe"
    }
  ],
  "lise_bom": [
    {
      "datum": "2026-04-02T22:00:00.000Z",
      "titel": "Topscorers_ familie-jubileum voor zusjes Pien en Jip Dicke",
      "bullet": "Staat op 7 goals na vijftien speelronden.",
      "link": "https://drive.google.com/file/d/1aRuLl3sPlKdye7gpamhIuZZoGdHkaWYe"
    }
  ],
  "thijmen_bosman": [
    {
      "datum": "2026-04-02T22:00:00.000Z",
      "titel": "Topscorers_ familie-jubileum voor zusjes Pien en Jip Dicke",
      "bullet": "Scoorde drie doelpunten tegen Victoria in een 4-1 zege.",
      "link": "https://drive.google.com/file/d/1aRuLl3sPlKdye7gpamhIuZZoGdHkaWYe"
    },
    {
      "datum": "2026-04-02T22:00:00.000Z",
      "titel": "Topscorers_ familie-jubileum voor zusjes Pien en Jip Dicke",
      "bullet": "Staat op negentien goals.",
      "link": "https://drive.google.com/file/d/1aRuLl3sPlKdye7gpamhIuZZoGdHkaWYe"
    },
    {
      "datum": "2026-04-02T22:00:00.000Z",
      "titel": "Topscorers_ familie-jubileum voor zusjes Pien en Jip Dicke",
      "bullet": "Maakte zijn derde hattrick in vier weken en vierde dit seizoen.",
      "link": "https://drive.google.com/file/d/1aRuLl3sPlKdye7gpamhIuZZoGdHkaWYe"
    }
  ],
  "cedric_terwel": [
    {
      "datum": "2026-04-02T22:00:00.000Z",
      "titel": "Topscorers_ familie-jubileum voor zusjes Pien en Jip Dicke",
      "bullet": "Staat op 16 goals na vijftien speelronden.",
      "link": "https://drive.google.com/file/d/1aRuLl3sPlKdye7gpamhIuZZoGdHkaWYe"
    },
    {
      "datum": "2026-04-02T22:00:00.000Z",
      "titel": "Topscorers_ familie-jubileum voor zusjes Pien en Jip Dicke",
      "bullet": "Is naaste volger van Thijmen Bosman.",
      "link": "https://drive.google.com/file/d/1aRuLl3sPlKdye7gpamhIuZZoGdHkaWYe"
    }
  ],
  "teun_mooldijk": [
    {
      "datum": "2026-04-02T22:00:00.000Z",
      "titel": "Topscorers_ familie-jubileum voor zusjes Pien en Jip Dicke",
      "bullet": "Staat op 15 goals na vijftien speelronden.",
      "link": "https://drive.google.com/file/d/1aRuLl3sPlKdye7gpamhIuZZoGdHkaWYe"
    }
  ],
  "tijn_stuve": [
    {
      "datum": "2026-04-02T22:00:00.000Z",
      "titel": "Topscorers_ familie-jubileum voor zusjes Pien en Jip Dicke",
      "bullet": "Staat op 15 goals na vijftien speelronden.",
      "link": "https://drive.google.com/file/d/1aRuLl3sPlKdye7gpamhIuZZoGdHkaWYe"
    }
  ],
  "pim_haring": [
    {
      "datum": "2026-04-02T22:00:00.000Z",
      "titel": "Topscorers_ familie-jubileum voor zusjes Pien en Jip Dicke",
      "bullet": "Staat op 15 goals na vijftien speelronden.",
      "link": "https://drive.google.com/file/d/1aRuLl3sPlKdye7gpamhIuZZoGdHkaWYe"
    }
  ],
  "casper_hafkamp": [
    {
      "datum": "2026-04-02T22:00:00.000Z",
      "titel": "Topscorers_ familie-jubileum voor zusjes Pien en Jip Dicke",
      "bullet": "Staat op 14 goals na vijftien speelronden.",
      "link": "https://drive.google.com/file/d/1aRuLl3sPlKdye7gpamhIuZZoGdHkaWYe"
    }
  ],
  "stijn_van_pelt": [
    {
      "datum": "2026-04-02T22:00:00.000Z",
      "titel": "Topscorers_ familie-jubileum voor zusjes Pien en Jip Dicke",
      "bullet": "Staat op 13 goals na vijftien speelronden.",
      "link": "https://drive.google.com/file/d/1aRuLl3sPlKdye7gpamhIuZZoGdHkaWYe"
    }
  ],
  "jim_van_de_venne": [
    {
      "datum": "2026-04-02T22:00:00.000Z",
      "titel": "Topscorers_ familie-jubileum voor zusjes Pien en Jip Dicke",
      "bullet": "Staat op 13 goals na vijftien speelronden.",
      "link": "https://drive.google.com/file/d/1aRuLl3sPlKdye7gpamhIuZZoGdHkaWYe"
    }
  ]
}